<?xml version="1.0" encoding="UTF-8" ?>
<root>
  <data>
    <title>Arethusa bulbosa</title>
    <family>Orchidaceae</family>
    <genus>Arethusa</genus>
    <species>bulbosa</species>
    <common_name>Swamp Pink</common_name>
    <french_common_name>Aréthus Bulbeuse</french_common_name>
    <plant_type>non-woody</plant_type>
    <habitat>Wetlands</habitat>
    <leaf_type>Simple</leaf_type>
    <leaf_arrangement>Opposite</leaf_arrangement>
    <leaf_blade_edges/>
    <flower_petal_colour/>
    <bloom_time></bloom_time>
    <armature></armature>
    <bark_texture></bark_texture>
    <growth_form></growth_form>
    <deciduous_or_coniferous></deciduous_or_coniferous>
    <leaves_per_node/>
    <leaf_divisions/>
    <spore_bearing_leaflets></spore_bearing_leaflets>
    <native_or_introduced_or_invasive></native_or_introduced_or_invasive>
    <rank></rank>
    <new_brunswick_county></new_brunswick_county>
    <image_preview/>
    <note>Dragon&#x27;s-mouth is endemic to northeastern North America. The genus Arethusa includes only this species and is named after a river nymph from Greek mythology. The flowers are showy and fragrant but offer little or no reward to the pollinator.</note>
  </data>
  <data>
    <title>Arethusa bulbosa</title>
    <family>Orchidaceae</family>
    <genus>Arethusa</genus>
    <species>bulbosa</species>
    <common_name>Swamp Pink</common_name>
    <french_common_name>Aréthus Bulbeuse</french_common_name>
    <plant_type>non-woody</plant_type>
    <habitat>Wetlands</habitat>
    <leaf_type>Simple</leaf_type>
    <leaf_arrangement>Opposite</leaf_arrangement>
    <leaf_blade_edges/>
    <flower_petal_colour/>
    <bloom_time></bloom_time>
    <armature></armature>
    <bark_texture></bark_texture>
    <growth_form></growth_form>
    <deciduous_or_coniferous></deciduous_or_coniferous>
    <leaves_per_node/>
    <leaf_divisions/>
    <spore_bearing_leaflets></spore_bearing_leaflets>
    <native_or_introduced_or_invasive></native_or_introduced_or_invasive>
    <rank></rank>
    <new_brunswick_county></new_brunswick_county>
    <image_preview/>
    <note>Dragon&#x27;s-mouth is endemic to northeastern North America. The genus Arethusa includes only this species and is named after a river nymph from Greek mythology. The flowers are showy and fragrant but offer little or no reward to the pollinator.</note>
  </data>
</root>
